ssl_sentinel/__about__.py
ssl_sentinel/__init__.py
ssl_sentinel/certificate.py
ssl_sentinel/main.py
ssl_sentinel-1.2.1.dist-info/METADATA
ssl_sentinel-1.2.1.dist-info/WHEEL
ssl_sentinel-1.2.1.dist-info/entry_points.txt
ssl_sentinel-1.2.1.dist-info/licenses/LICENSE
ssl_sentinel-1.2.1.dist-info/RECORD
