Metadata-Version: 2.4
Name: ssl-sentinel
Version: 1.2.1
Summary: A command-line tool for checking SSL/TLS certificate validity and expiration dates.
Project-URL: Homepage, https://github.com/janoantelo7/ssl-sentinel
Project-URL: Repository, https://github.com/janoantelo7/ssl-sentinel.git
Project-URL: Documentation, https://github.com/janoantelo7/ssl-sentinel#readme
Project-URL: Issues, https://github.com/janoantelo7/ssl-sentinel/issues
Author: Alejandro Antelo Abelenda
License: MIT
License-File: LICENSE
Requires-Python: >=3.6
